ccc_main.py
cccmd-0.3.1.dist-info/licenses/LICENSE
lib/ccc_claude.py
lib/ccc_commands.py
lib/ccc_dialog_monitor.py
lib/ccc_manager.py
lib/ccc_monitor.py
lib/claude_session_log.py
cccmd-0.3.1.dist-info/METADATA
cccmd-0.3.1.dist-info/WHEEL
cccmd-0.3.1.dist-info/entry_points.txt
cccmd-0.3.1.dist-info/top_level.txt
cccmd-0.3.1.dist-info/RECORD
