Metadata-Version: 2.4
Name: cccmd
Version: 0.3.1
Summary: Collective Context Commander - Multi-Agent AI Orchestration Tool
Author-email: Collective Context Team <team@collective-context.org>
License: MIT
Project-URL: Homepage, https://collective-context.org
Project-URL: Documentation, https://collective-context.org/ccc/
Project-URL: Repository, https://github.com/collective-context/ccc.git
Project-URL: Issues, https://github.com/collective-context/ccc/issues
Project-URL: Changelog, https://github.com/collective-context/ccc/blob/main/CHANGELOG.md
Keywords: ai,orchestration,multi-agent,cli,collective-context,aider
Classifier: Development Status :: 4 - Beta
Classifier: Environment :: Console
Classifier: Intended Audience :: Developers
Classifier: License :: OSI Approved :: MIT License
Classifier: Operating System :: OS Independent
Classifier: Programming Language :: Python :: 3
Classifier: Programming Language :: Python :: 3.8
Classifier: Programming Language :: Python :: 3.9
Classifier: Programming Language :: Python :: 3.10
Classifier: Programming Language :: Python :: 3.11
Classifier: Programming Language :: Python :: 3.12
Classifier: Topic :: Software Development :: Libraries :: Python Modules
Classifier: Topic :: Scientific/Engineering :: Artificial Intelligence
Requires-Python: >=3.8
License-File: LICENSE
Requires-Dist: click>=8.0
Requires-Dist: rich>=10.0
Requires-Dist: pydantic>=2.0
Requires-Dist: requests>=2.25.0
Requires-Dist: pyyaml>=6.0
Provides-Extra: dev
Requires-Dist: pytest>=7.0; extra == "dev"
Requires-Dist: pytest-cov>=4.0; extra == "dev"
Requires-Dist: black>=23.0; extra == "dev"
Requires-Dist: ruff>=0.1.0; extra == "dev"
Requires-Dist: mypy>=1.0; extra == "dev"
Requires-Dist: build>=0.10.0; extra == "dev"
Requires-Dist: twine>=4.0.0; extra == "dev"
Dynamic: license-file
